helpfulgremlin/__init__.py
helpfulgremlin/detector.py
helpfulgremlin/main.py
helpfulgremlin/patterns.yaml
helpfulgremlin/scanner.py
helpfulgremlin-0.1.2.dist-info/WHEEL
helpfulgremlin-0.1.2.dist-info/entry_points.txt
helpfulgremlin-0.1.2.dist-info/METADATA
helpfulgremlin-0.1.2.dist-info/RECORD
