Metadata-Version: 2.3
Name: helpfulgremlin
Version: 0.1.2
Summary: Add your description here
Author-email: udit.ramawat@gmail.com
License: MIT License
Classifier: License :: OSI Approved :: MIT License
Classifier: Programming Language :: Python :: 3
Requires-Dist: pathspec>=1.0.4
Requires-Dist: pyyaml>=6.0.3
Requires-Dist: rich>=14.3.1
Requires-Dist: typer>=0.21.1
Requires-Python: >=3.13
